animalapi/__init__.py
animalapi-0.0.4.dist-info/LICENSE
animalapi-0.0.4.dist-info/METADATA
animalapi-0.0.4.dist-info/WHEEL
animalapi-0.0.4.dist-info/top_level.txt
animalapi-0.0.4.dist-info/RECORD
