Metadata-Version: 2.1
Name: animalapi
Version: 0.0.4
Summary: A simple Python wrapper for the some-random-api.ml API.
Author: Ashutosh Das
Author-email: ashutoshdas2004@gmail.com
Project-URL: Bug Tracker, https://github.com/DARKPOISON-yt/animalapi/issues
Project-URL: Source Code, https://github.com/DARKPOISON-yt/animalapi
Keywords: animal,api,wrapper,images,facts
Classifier: Development Status :: 3 - Alpha
Classifier: Intended Audience :: Developers
Classifier: Topic :: Software Development :: Libraries :: Python Modules
Classifier: License :: OSI Approved :: MIT License
Classifier: Programming Language :: Python :: 3
Classifier: Programming Language :: Python :: 3.6
Classifier: Programming Language :: Python :: 3.7
Classifier: Programming Language :: Python :: 3.8
Classifier: Programming Language :: Python :: 3.9
Classifier: Operating System :: Unix
Classifier: Operating System :: MacOS :: MacOS X
Classifier: Operating System :: Microsoft :: Windows
License-File: LICENSE
Requires-Dist: requests
Requires-Dist: random
